{
  "baseUrl": "http://localhost:3000",
  "fileServerFolder": "e2e/cypress/",
  "fixturesFolder": "e2e/cypress/fixtures",
  "ignoreTestFiles": ["**/__snapshots__/*", "**/__image_snapshots__/*"],
  "integrationFolder": "e2e/cypress/integration",
  "pluginsFile": "e2e/cypress/plugins",
  "screenshotsFolder": "e2e/cypress/screenshots",
  "supportFile": "e2e/cypress/support",
  "videosFolder": "e2e/cypress/videos",
  "env": {
    "cypress-plugin-snapshots": {
      "imageConfig": {
        "threshold": 0.005
      }
    }
  }
}
